{"settings":[{"key":"appName","valueType":"string","defaultValue":"Tempo Trainer","configTitle":"AppNameTitle","configPrompt":null,"configHelpUrl":null,"configError":null,"configType":"alphaNumeric","configReadonly":true,"configRequired":false,"configOptions":null,"configMin":null,"configMax":null,"configMaxLength":null},{"key":"appVersion","valueType":"string","defaultValue":"1.1.0","configTitle":"AppVersionTitle","configPrompt":null,"configHelpUrl":null,"configError":null,"configType":"alphaNumeric","configReadonly":true,"configRequired":false,"configOptions":null,"configMin":null,"configMax":null,"configMaxLength":null},{"key":"mode","valueType":"number","defaultValue":0,"configTitle":"modeTitle","configPrompt":null,"configHelpUrl":null,"configError":null,"configType":"list","configReadonly":false,"configRequired":true,"configOptions":[{"display":"modeRate","value":0},{"display":"modeBpm","value":1}],"configMin":null,"configMax":null,"configMaxLength":null},{"key":"onViewOnly","valueType":"number","defaultValue":0,"configTitle":"onViewOnlyTitle","configPrompt":"onViewOnlyPrompt","configHelpUrl":"https://github.com/adamml/tempo-trainer/blob/master/doc/on-view-only-settings.md","configError":null,"configType":"list","configReadonly":false,"configRequired":true,"configOptions":[{"display":"onViewOnlyFalse","value":0},{"display":"onViewOnlyTrue","value":1}],"configMin":null,"configMax":null,"configMaxLength":null},{"key":"notify","valueType":"number","defaultValue":0,"configTitle":"notifyTitle","configPrompt":null,"configHelpUrl":null,"configError":null,"configType":"list","configReadonly":false,"configRequired":true,"configOptions":[{"display":"notifyVibrate","value":0},{"display":"notifyVibrateTone","value":1},{"display":"notifyTone","value":2},{"display":"notifyVisual","value":3}],"configMin":null,"configMax":null,"configMaxLength":null},{"key":"rate","valueType":"number","defaultValue":1,"configTitle":"rateTitle","configPrompt":"ratePrompt","configHelpUrl":"https://github.com/adamml/tempo-trainer/blob/master/doc/rate-settings.md","configError":null,"configType":"numeric","configReadonly":false,"configRequired":true,"configOptions":null,"configMin":1,"configMax":599,"configMaxLength":null}],"languages":{"valyrian":{"AppVersionTitle":"Version","onViewOnlyFalse":"No","notifyVibrate":"Vibrate + Visual","AppNameTitle":"Datafield","notifyVibrateTone":"Vibrate, Tone + Visual","modeTitle":"Mode","notifyTone":"Tone + Visual","modeRate":"Rate","notifyTitle":"Notification Mode","AppName":"Tempo Trainer","rateTitle":"Rate","onViewOnlyTitle":"Notify only when data field is visible","notifyVisual":"Visual Only","onViewOnlyPrompt":"Select \\\"no\\\" to have the data field use vibration and/or tone alerts at all times when the data field is enabled for an activity (default); select \\\"yes\\\" to only have alerts active when the data field is in view on the watch screen.","ratePrompt":"In rate mode this indicates the number of seconds between an alert. In this mode the range is 1-599.\r\rIn Beats Per Minute mode this indicates the number of alerts to be played each minute. Although the range which may be input remains at 1-599 (as a limitation of ConnectIQ), the functional range for the datafield is 1-60 and the datafield will adjust dynamically to this range.","onViewOnlyTrue":"Yes","modeBpm":"Beats Per Minute"}}}